{
  "error": false,
  "syncType": "LINE_SYNCED",
  "lines": [
    {
      "startTimeMs": "8890",
      "words": "Gleaming, twinkling",
      "syllables": [],
      "endTimeMs": "0"
    },
    {
      "startTimeMs": "13100",
      "words": "Eyes like sinking ships on waters",
      "syllables": [],
      "endTimeMs": "0"
    },
    {
      "startTimeMs": "21400",
      "words": "So inviting, I almost jump in",
      "syllables": [],
      "endTimeMs": "0"
    },
    {
      "startTimeMs": "25760",
      "words": "But I don't like a gold rush, gold rush",
      "syllables": [],
      "endTimeMs": "0"
    },
    {
      "startTimeMs": "29230",
      "words": "I don't like anticipating my face in a red flush",
      "syllables": [],
      "endTimeMs": "0"
    },
    {
      "startTimeMs": "33560",
      "words": "I don't like that anyone would die to feel your touch",
      "syllables": [],
      "endTimeMs": "0"
    },
    {
      "startTimeMs": "37720",
      "words": "Everybody wants you",
      "syllables": [],
      "endTimeMs": "0"
    },
    {
      "startTimeMs": "39750",
      "words": "Everybody wonders what it would be like to love you",
      "syllables": [],
      "endTimeMs": "0"
    },
    {
      "startTimeMs": "44150",
      "words": "Walk past, quick brush",
      "syllables": [],
      "endTimeMs": "0"
    },
    {
      "startTimeMs": "46380",
      "words": "I don't like slow motion, double vision in rose blush",
      "syllables": [],
      "endTimeMs": "0"
    },
    {
      "startTimeMs": "50670",
      "words": "I don't like that falling feels like flying 'til the bone crush",
      "syllables": [],
      "endTimeMs": "0"
    },
    {
      "startTimeMs": "54960",
      "words": "Everybody wants you",
      "syllables": [],
      "endTimeMs": "0"
    },
    {
      "startTimeMs": "57770",
      "words": "But I don't like a gold rush",
      "syllables": [],
      "endTimeMs": "0"
    },
    {
      "startTimeMs": "60460",
      "words": "What must it be like to grow up that beautiful?",
      "syllables": [],
      "endTimeMs": "0"
    },
    {
      "startTimeMs": "66520",
      "words": "With your hair falling into place like dominoes",
      "syllables": [],
      "endTimeMs": "0"
    },
    {
      "startTimeMs": "69710",
      "words": "I see me padding across your wooden floors",
      "syllables": [],
      "endTimeMs": "0"
    },
    {
      "startTimeMs": "74960",
      "words": "With my Eagles T-shirt hanging from the door",
      "syllables": [],
      "endTimeMs": "0"
    },
    {
      "startTimeMs": "77950",
      "words": "At dinner parties, I call you out on your contrarian shit",
      "syllables": [],
      "endTimeMs": "0"
    },
    {
      "startTimeMs": "81980",
      "words": "And the coastal town we wandered 'round",
      "syllables": [],
      "endTimeMs": "0"
    },
    {
      "startTimeMs": "84250",
      "words": "Had nevеr seen a love as pure as it",
      "syllables": [],
      "endTimeMs": "0"
    },
    {
      "startTimeMs": "87590",
      "words": "And then it fadеs into the gray of my day-old tea",
      "syllables": [],
      "endTimeMs": "0"
    },
    {
      "startTimeMs": "91720",
      "words": "'Cause it could never be",
      "syllables": [],
      "endTimeMs": "0"
    },
    {
      "startTimeMs": "94280",
      "words": "'Cause I don't like a gold rush, gold rush",
      "syllables": [],
      "endTimeMs": "0"
    },
    {
      "startTimeMs": "97830",
      "words": "I don't like anticipating my face in a red flush",
      "syllables": [],
      "endTimeMs": "0"
    },
    {
      "startTimeMs": "102080",
      "words": "I don't like that anyone would die to feel your touch",
      "syllables": [],
      "endTimeMs": "0"
    },
    {
      "startTimeMs": "106350",
      "words": "Everybody wants you",
      "syllables": [],
      "endTimeMs": "0"
    },
    {
      "startTimeMs": "108430",
      "words": "Everybody wonders what it would be like to love you",
      "syllables": [],
      "endTimeMs": "0"
    },
    {
      "startTimeMs": "112770",
      "words": "Walk past, quick brush",
      "syllables": [],
      "endTimeMs": "0"
    },
    {
      "startTimeMs": "114870",
      "words": "I don't like slow motion, double vision in rose blush",
      "syllables": [],
      "endTimeMs": "0"
    },
    {
      "startTimeMs": "119350",
      "words": "I don't like that falling feels like flying 'til the bone crush",
      "syllables": [],
      "endTimeMs": "0"
    },
    {
      "startTimeMs": "123460",
      "words": "Everybody wants you",
      "syllables": [],
      "endTimeMs": "0"
    },
    {
      "startTimeMs": "126360",
      "words": "But I don't like a gold rush",
      "syllables": [],
      "endTimeMs": "0"
    },
    {
      "startTimeMs": "128950",
      "words": "What must it be like to grow up that beautiful?",
      "syllables": [],
      "endTimeMs": "0"
    },
    {
      "startTimeMs": "135060",
      "words": "With your hair falling into place like dominoes",
      "syllables": [],
      "endTimeMs": "0"
    },
    {
      "startTimeMs": "138020",
      "words": "My mind turns your life into folklore",
      "syllables": [],
      "endTimeMs": "0"
    },
    {
      "startTimeMs": "143390",
      "words": "I can't dare to dream about you anymore",
      "syllables": [],
      "endTimeMs": "0"
    },
    {
      "startTimeMs": "146430",
      "words": "At dinner parties, I won't call you out on your contrarian shit",
      "syllables": [],
      "endTimeMs": "0"
    },
    {
      "startTimeMs": "150750",
      "words": "And the coastal town we never found",
      "syllables": [],
      "endTimeMs": "0"
    },
    {
      "startTimeMs": "152840",
      "words": "Will never see a love as pure as it",
      "syllables": [],
      "endTimeMs": "0"
    },
    {
      "startTimeMs": "156080",
      "words": "'Cause it fades into the gray of my day-old tea",
      "syllables": [],
      "endTimeMs": "0"
    },
    {
      "startTimeMs": "160230",
      "words": "'Cause it will never be",
      "syllables": [],
      "endTimeMs": "0"
    },
    {
      "startTimeMs": "163020",
      "words": "Gleaming, twinkling",
      "syllables": [],
      "endTimeMs": "0"
    },
    {
      "startTimeMs": "167540",
      "words": "Eyes like sinking ships on waters",
      "syllables": [],
      "endTimeMs": "0"
    },
    {
      "startTimeMs": "175900",
      "words": "So inviting, I almost jump in",
      "syllables": [],
      "endTimeMs": "0"
    },
    {
      "startTimeMs": "179830",
      "words": "",
      "syllables": [],
      "endTimeMs": "0"
    }
  ]
}