{
  "error": false,
  "syncType": "LINE_SYNCED",
  "lines": [
    {
      "startTimeMs": "15630",
      "words": "We were both young when I first saw you",
      "syllables": [],
      "endTimeMs": "0"
    },
    {
      "startTimeMs": "19800",
      "words": "I close my eyes and the flashback starts",
      "syllables": [],
      "endTimeMs": "0"
    },
    {
      "startTimeMs": "23560",
      "words": "I'm standing there",
      "syllables": [],
      "endTimeMs": "0"
    },
    {
      "startTimeMs": "26790",
      "words": "On a balcony in summer air",
      "syllables": [],
      "endTimeMs": "0"
    },
    {
      "startTimeMs": "32180",
      "words": "See the lights, see the party, the ball gowns",
      "syllables": [],
      "endTimeMs": "0"
    },
    {
      "startTimeMs": "36000",
      "words": "See you make your way through the crowd",
      "syllables": [],
      "endTimeMs": "0"
    },
    {
      "startTimeMs": "39740",
      "words": "And say \"Hello\"",
      "syllables": [],
      "endTimeMs": "0"
    },
    {
      "startTimeMs": "42900",
      "words": "Little did I know",
      "syllables": [],
      "endTimeMs": "0"
    },
    {
      "startTimeMs": "48110",
      "words": "That you were Romeo, you were throwing pebbles",
      "syllables": [],
      "endTimeMs": "0"
    },
    {
      "startTimeMs": "52190",
      "words": "And my daddy said, \"Stay away from Juliet\"",
      "syllables": [],
      "endTimeMs": "0"
    },
    {
      "startTimeMs": "55710",
      "words": "And I was crying on the staircase",
      "syllables": [],
      "endTimeMs": "0"
    },
    {
      "startTimeMs": "58720",
      "words": "Begging you, \"Please don't go\"",
      "syllables": [],
      "endTimeMs": "0"
    },
    {
      "startTimeMs": "63000",
      "words": "And I said",
      "syllables": [],
      "endTimeMs": "0"
    },
    {
      "startTimeMs": "64030",
      "words": "\"Romeo take me somewhere we can be alone",
      "syllables": [],
      "endTimeMs": "0"
    },
    {
      "startTimeMs": "68260",
      "words": "I'll be waiting, all there's left to do is run",
      "syllables": [],
      "endTimeMs": "0"
    },
    {
      "startTimeMs": "72000",
      "words": "You'll be the prince, and I'll be the princess",
      "syllables": [],
      "endTimeMs": "0"
    },
    {
      "startTimeMs": "76320",
      "words": "It's a love story, baby, just say yes\"",
      "syllables": [],
      "endTimeMs": "0"
    },
    {
      "startTimeMs": "81820",
      "words": "♪",
      "syllables": [],
      "endTimeMs": "0"
    },
    {
      "startTimeMs": "85020",
      "words": "So I sneak out to the garden to see you",
      "syllables": [],
      "endTimeMs": "0"
    },
    {
      "startTimeMs": "88250",
      "words": "We keep quiet 'cause we're dead if they knew",
      "syllables": [],
      "endTimeMs": "0"
    },
    {
      "startTimeMs": "92020",
      "words": "So close your eyes",
      "syllables": [],
      "endTimeMs": "0"
    },
    {
      "startTimeMs": "95060",
      "words": "Escape this town for a little while, oh, oh",
      "syllables": [],
      "endTimeMs": "0"
    },
    {
      "startTimeMs": "100400",
      "words": "'Cause you were Romeo, I was a scarlet letter",
      "syllables": [],
      "endTimeMs": "0"
    },
    {
      "startTimeMs": "104190",
      "words": "And my daddy said, \"Stay away from Juliet\"",
      "syllables": [],
      "endTimeMs": "0"
    },
    {
      "startTimeMs": "108050",
      "words": "But you were everything to me",
      "syllables": [],
      "endTimeMs": "0"
    },
    {
      "startTimeMs": "110280",
      "words": "I was begging you, \"Please don't go\"",
      "syllables": [],
      "endTimeMs": "0"
    },
    {
      "startTimeMs": "114890",
      "words": "And I said",
      "syllables": [],
      "endTimeMs": "0"
    },
    {
      "startTimeMs": "116450",
      "words": "\"Romeo, take me somewhere we can be alone",
      "syllables": [],
      "endTimeMs": "0"
    },
    {
      "startTimeMs": "120740",
      "words": "I'll be waiting, all there's left to do is run",
      "syllables": [],
      "endTimeMs": "0"
    },
    {
      "startTimeMs": "124840",
      "words": "You'll be the prince, and I'll be the princess",
      "syllables": [],
      "endTimeMs": "0"
    },
    {
      "startTimeMs": "128640",
      "words": "It's a love story, baby, just say yes\"",
      "syllables": [],
      "endTimeMs": "0"
    },
    {
      "startTimeMs": "133240",
      "words": "Romeo, save me, they're trying to tell me how to feel",
      "syllables": [],
      "endTimeMs": "0"
    },
    {
      "startTimeMs": "136880",
      "words": "This love is difficult, but it's real",
      "syllables": [],
      "endTimeMs": "0"
    },
    {
      "startTimeMs": "141140",
      "words": "Don't be afraid, we'll make it out of this mess",
      "syllables": [],
      "endTimeMs": "0"
    },
    {
      "startTimeMs": "144920",
      "words": "It's a love story, baby, just say yes",
      "syllables": [],
      "endTimeMs": "0"
    },
    {
      "startTimeMs": "150240",
      "words": "",
      "syllables": [],
      "endTimeMs": "0"
    },
    {
      "startTimeMs": "152270",
      "words": "Oh, oh-oh",
      "syllables": [],
      "endTimeMs": "0"
    },
    {
      "startTimeMs": "156880",
      "words": "♪",
      "syllables": [],
      "endTimeMs": "0"
    },
    {
      "startTimeMs": "164620",
      "words": "I got tired of waiting",
      "syllables": [],
      "endTimeMs": "0"
    },
    {
      "startTimeMs": "168520",
      "words": "Wondering if you were ever coming around",
      "syllables": [],
      "endTimeMs": "0"
    },
    {
      "startTimeMs": "172540",
      "words": "My faith in you was fading",
      "syllables": [],
      "endTimeMs": "0"
    },
    {
      "startTimeMs": "176960",
      "words": "When I met you on the outskirts of town",
      "syllables": [],
      "endTimeMs": "0"
    },
    {
      "startTimeMs": "180670",
      "words": "And I said",
      "syllables": [],
      "endTimeMs": "0"
    },
    {
      "startTimeMs": "181190",
      "words": "\"Romeo, save me, I've been feeling so alone",
      "syllables": [],
      "endTimeMs": "0"
    },
    {
      "startTimeMs": "185480",
      "words": "I keep waiting for you, but you never come",
      "syllables": [],
      "endTimeMs": "0"
    },
    {
      "startTimeMs": "189520",
      "words": "Is this in my head? I don't know what to think\"",
      "syllables": [],
      "endTimeMs": "0"
    },
    {
      "startTimeMs": "193120",
      "words": "He knelt to the ground and pulled out a ring",
      "syllables": [],
      "endTimeMs": "0"
    },
    {
      "startTimeMs": "197180",
      "words": "And said",
      "syllables": [],
      "endTimeMs": "0"
    },
    {
      "startTimeMs": "198280",
      "words": "\"Marry me, Juliet, you'll never have to be alone",
      "syllables": [],
      "endTimeMs": "0"
    },
    {
      "startTimeMs": "201400",
      "words": "I love you, and that's all I really know",
      "syllables": [],
      "endTimeMs": "0"
    },
    {
      "startTimeMs": "205200",
      "words": "I talked to your dad, go pick out a white dress",
      "syllables": [],
      "endTimeMs": "0"
    },
    {
      "startTimeMs": "209460",
      "words": "It's a love story, baby, just say yes\"",
      "syllables": [],
      "endTimeMs": "0"
    },
    {
      "startTimeMs": "216430",
      "words": "Oh, oh-oh",
      "syllables": [],
      "endTimeMs": "0"
    },
    {
      "startTimeMs": "220460",
      "words": "Oh, oh-oh, oh",
      "syllables": [],
      "endTimeMs": "0"
    },
    {
      "startTimeMs": "225520",
      "words": "'Cause we were both young when I first saw you",
      "syllables": [],
      "endTimeMs": "0"
    },
    {
      "startTimeMs": "229650",
      "words": "",
      "syllables": [],
      "endTimeMs": "0"
    }
  ]
}